WPSProtocol/InitialFunctions.py
WPSProtocol/Module_RotationAngleErrorsDoubleAveraging.py
WPSProtocol/Module_WalshPSeq.py
WPSProtocol/Part_2A.py
WPSProtocol/TestingFile.py
WPSProtocol/__init__.py
WPSProtocol/__pycache__/InitialFunctions.cpython-38.pyc
WPSProtocol/__pycache__/Module_WalshPSeq.cpython-38.pyc
WPSProtocol/__pycache__/Part_2A.cpython-38.pyc
WPSProtocol/__pycache__/__init__.cpython-38.pyc
WPSProtocol-1.1.post3.dist-info/LICENSE
WPSProtocol-1.1.post3.dist-info/METADATA
WPSProtocol-1.1.post3.dist-info/WHEEL
WPSProtocol-1.1.post3.dist-info/top_level.txt
WPSProtocol-1.1.post3.dist-info/RECORD
